opnsense_helper/__init__.py
opnsense_helper/opnsense_helper.py
opnsense_helper/commands/__init__.py
opnsense_helper/commands/commands.py
opnsense_helper/config_manager/__init__.py
opnsense_helper/config_manager/config_manager.py
opnsense_helper/scripts/__init__.py
opnsense_helper/scripts/scripts.py
opnsense_helper/utils/__init__.py
opnsense_helper/utils/baseclass.py
opnsense_helper/utils/exec_class.py
opnsense_helper/utils/frontend_utils.py
opnsense_helper/utils/utils.py
opnsense_helper-0.1.26.dist-info/METADATA
opnsense_helper-0.1.26.dist-info/WHEEL
opnsense_helper-0.1.26.dist-info/top_level.txt
opnsense_helper-0.1.26.dist-info/RECORD
